{"childNodeDatas":[{"healthState":"Uninitialized","id":"9813e0c2-d0a3-4556-bef0-344ec3cb22bc","monitorId":"c4192440-55eb-398e-f931-d3fd31ca33bf","monitorDisplayName":"Security","monitorName":"System.Health.SecurityState","lastTimeModified":"31/10/2020 2:38:13"},{"healthState":"Uninitialized","id":"38b8cf81-9d35-4c0e-83be-850063288a9c","monitorId":"4fea8a72-7ed1-7621-c3a3-103ef0e91574","monitorDisplayName":"Configuration","monitorName":"System.Health.ConfigurationState","lastTimeModified":"31/10/2020 2:38:13"},{"healthState":"Uninitialized","id":"bddcaea7-a571-4dfe-b15d-9b23795e7478","monitorId":"7db3eece-fd0d-fddd-3af7-f8371a914874","monitorDisplayName":"Performance","monitorName":"System.Health.PerformanceState","lastTimeModified":"31/10/2020 2:38:13"},{"healthState":"Success","id":"41676846-9aee-4f40-8980-cef9babbc2ee","monitorId":"a6c69968-61aa-a6b9-db6e-83a0da6110ea","monitorDisplayName":"Availability","monitorName":"System.Health.AvailabilityState","lastTimeModified":"06/08/2021 20:39:14"}],"alertCount":0,"healthState":"Success","objectId":"6d39cf14-2839-0eca-2b7c-2c0ebc684ba4"}